snapr-0.5.0.dist-info/METADATA
snapr-0.5.0.dist-info/WHEEL
snapr/__init__.py
snapr/__init__.pyi
snapr/py.typed
snapr/snapr.cpython-39-darwin.so
snapr-0.5.0.dist-info/RECORD
