Metadata-Version: 2.3
Name: snapr
Version: 0.5.0
Classifier: Programming Language :: Rust
Classifier: Programming Language :: Python :: Implementation :: CPython
Classifier: Programming Language :: Python :: Implementation :: PyPy
Summary: Library enabling a flexible and frictionless way to render snapshots of maps with overlayed geometries.
Author: c1m50c <58411864+c1m50c@users.noreply.github.com>
Author-email: c1m50c <58411864+c1m50c@users.noreply.github.com>
License: MIT
Requires-Python: >=3.8
Project-URL: Issues, https://github.com/c1m50c/snapr/issues
Project-URL: Repository, https://github.com/c1m50c/snapr
